myfunctionjt.py
RiskmgmtLibrary_Final_jt393-1.dist-info/METADATA
RiskmgmtLibrary_Final_jt393-1.dist-info/WHEEL
RiskmgmtLibrary_Final_jt393-1.dist-info/top_level.txt
RiskmgmtLibrary_Final_jt393-1.dist-info/RECORD
