Metadata-Version: 2.1
Name: RiskmgmtLibrary-Final-jt393
Version: 1
Summary: Risk management
Author: Jingyu Tan
Author-email: t1169242950@gmail.com
